swarmtube/__init__.py
swarmtube/definitions.py
swarmtube/swarmtube.py
swarmtube/cli/__init__.py
swarmtube/cli/config.py
swarmtube/cli/inventory.py
swarmtube/cli/main.py
swarmtube/cli/publish.py
swarmtube/cli/script.py
swarmtube/cli/setup.py
swarmtube/cli/surreal.py
swarmtube/cli/sync.py
swarmtube/cli/task.py
swarmtube/cli/wingdbstub.py
swarmtube/cli/workspace.py
swarmtube/helpers/__init__.py
swarmtube/helpers/faker.py
swarmtube/helpers/general.py
swarmtube/helpers/loaders.py
swarmtube/helpers/models.py
swarmtube/helpers/surreal.py
swarmtube/logic/__init__.py
swarmtube/logic/crawler.py
swarmtube/logic/inventory.py
swarmtube/logic/swarmtube.py
swarmtube/mappers/__init__.py
swarmtube/mappers/inventory.py
swarmtube/models/__init__.py
swarmtube/models/base.py
swarmtube/models/config.py
swarmtube/models/enums.py
swarmtube/models/inventory.py
swarmtube/models/particle.py
swarmtube/models/script.py
swarmtube/models/swarmtube.py
swarmtube/models/task.py
swarmtube/particles/__init__.py
swarmtube/particles/fiware.py
swarmtube/ports/__init__.py
swarmtube/ports/preferences.py
swarmtube/storage/__init__.py
swarmtube/storage/surreal.py
swarmtube-0.1.357.dist-info/AUTHORS.rst
swarmtube-0.1.357.dist-info/LICENSE
swarmtube-0.1.357.dist-info/METADATA
swarmtube-0.1.357.dist-info/WHEEL
swarmtube-0.1.357.dist-info/entry_points.txt
swarmtube-0.1.357.dist-info/top_level.txt
swarmtube-0.1.357.dist-info/RECORD
