Metadata-Version: 2.2
Name: swarmtube
Version: 0.1.357
Summary: Swarm Workflow based on Tubes
Home-page: https://github.com/asterio.gonzalez/swarmtube
Author: Asterio Gonzalez
Author-email: asterio.gonzalez@gmail.com
License: MIT license
Keywords: swarmtube
Classifier: Development Status :: 2 - Pre-Alpha
Classifier: Intended Audience :: Developers
Classifier: License :: OSI Approved :: MIT License
Classifier: Natural Language :: English
Classifier: Programming Language :: Python :: 3.10
Classifier: Programming Language :: Python :: 3.11
Requires-Python: >=3.10
License-File: LICENSE
License-File: AUTHORS.rst
Requires-Dist: agptools>=0.1.357
Requires-Dist: aiocache
Requires-Dist: aiohttp
Requires-Dist: Click
Requires-Dist: datamodel-code-generator
Requires-Dist: datamodel-code-generator[graphql]
Requires-Dist: datamodel-code-generator[http]
Requires-Dist: faker
Requires-Dist: fastapi
Requires-Dist: geomdl
Requires-Dist: geopy
Requires-Dist: glom
Requires-Dist: jmespath
Requires-Dist: pydantic
Requires-Dist: matplotlib
Requires-Dist: requests
Requires-Dist: rich
Requires-Dist: surrealist==1.0.8
Requires-Dist: syncmodels>=0.1.357
Requires-Dist: uvicorn
Requires-Dist: uvloop
Requires-Dist: watchfiles
Requires-Dist: websockets>=11.0
Dynamic: author
Dynamic: author-email
Dynamic: classifier
Dynamic: description
Dynamic: home-page
Dynamic: keywords
Dynamic: license
Dynamic: requires-dist
Dynamic: requires-python
Dynamic: summary
